ora/__init__.py
ora/calendar.py
ora/date.py
ora/date_expr.py
ora/daytime.py
ora/ext.cpython-314-x86_64-linux-gnu.so
ora/util.py
ora/weekday.py
ora/calendars/usa-federal-businessdays.cal
ora/calendars/usa-federal-holidays.cal
ora/np/__init__.py
ora/test/data.py
ora/test/june18.cal
ora/test/test_calendar.py
ora/test/test_date_basic.py
ora/test/test_date_datenum.py
ora/test/test_date_math.py
ora/test/test_date_parts.py
ora/test/test_daytime_basic.py
ora/test/test_fmt.py
ora/test/test_from_local.py
ora/test/test_functions.py
ora/test/test_local.py
ora/test/test_np_date.py
ora/test/test_np_daytime.py
ora/test/test_np_functions.py
ora/test/test_np_time.py
ora/test/test_np_ufuncs_time.py
ora/test/test_parse_date.py
ora/test/test_parse_daytime.py
ora/test/test_parse_time.py
ora/test/test_time_basic.py
ora/test/test_time_zone.py
ora/test/test_time_zone_dir.py
ora/test/test_vs_zoneinfo.py
ora/test/tools.py
ora/zoneinfo/+VERSION
ora/zoneinfo/CET
ora/zoneinfo/CST6CDT
ora/zoneinfo/Cuba
ora/zoneinfo/EET
ora/zoneinfo/EST
ora/zoneinfo/EST5EDT
ora/zoneinfo/Egypt
ora/zoneinfo/Eire
ora/zoneinfo/Factory
ora/zoneinfo/GB
ora/zoneinfo/GB-Eire
ora/zoneinfo/GMT
ora/zoneinfo/GMT+0
ora/zoneinfo/GMT-0
ora/zoneinfo/GMT0
ora/zoneinfo/Greenwich
ora/zoneinfo/HST
ora/zoneinfo/Hongkong
ora/zoneinfo/Iceland
ora/zoneinfo/Iran
ora/zoneinfo/Israel
ora/zoneinfo/Jamaica
ora/zoneinfo/Japan
ora/zoneinfo/Kwajalein
ora/zoneinfo/Libya
ora/zoneinfo/MET
ora/zoneinfo/MST
ora/zoneinfo/MST7MDT
ora/zoneinfo/NZ
ora/zoneinfo/NZ-CHAT
ora/zoneinfo/Navajo
ora/zoneinfo/PRC
ora/zoneinfo/PST8PDT
ora/zoneinfo/Poland
ora/zoneinfo/Portugal
ora/zoneinfo/ROC
ora/zoneinfo/ROK
ora/zoneinfo/Singapore
ora/zoneinfo/Turkey
ora/zoneinfo/UCT
ora/zoneinfo/UTC
ora/zoneinfo/Universal
ora/zoneinfo/W-SU
ora/zoneinfo/WET
ora/zoneinfo/Zulu
ora/zoneinfo/iso3166.tab
ora/zoneinfo/leapseconds
ora/zoneinfo/tzdata.zi
ora/zoneinfo/zone.tab
ora-0.10.2.dist-info/METADATA
ora-0.10.2.dist-info/WHEEL
ora-0.10.2.dist-info/top_level.txt
ora-0.10.2.dist-info/RECORD
ora-0.10.2.dist-info/licenses/LICENSE
